bruhbook/__init__.py
bruhbook/bruhbook.py
bruhbook/bruhbookerrors.py
bruhbook-1.0.17.dist-info/LICENSE
bruhbook-1.0.17.dist-info/METADATA
bruhbook-1.0.17.dist-info/WHEEL
bruhbook-1.0.17.dist-info/RECORD
